Workbook

Sheet README
A1: ROI Calculator — JM Consulting AI Opportunity Audit
A3: Versión | B3: v1.0.0
A4: Uso | B4: Este workbook calcula el ROI esperado de cada oportunidad de IA identificada en el audit.
A5: Convenciones de color
A6: Azul | B6: Inputs hardcoded — los que el consultor ajusta por cliente.
A7: Negro | B7: Fórmulas y cálculos — no tocar.
A8: Verde | B8: Links entre sheets del mismo workbook.
A9: Amarillo (fondo) | B9: Asunciones clave que requieren validación con el cliente.
A11: Orden de uso | B11: 1. Completar Supuestos. 2. Poblar Task_Map con tareas del cliente. 3. Identificar Opportunities y valorar impacto. 4. Revisar Dashboard. 5. Validar Sensitivity.
A13: Sheets
A14: 1. README | B14: Este sheet — cómo usar el modelo.
A15: 2. Supuestos | B15: Inputs base del cliente: volumen, costo hora, horizonte, discount.
A16: 3. Task_Map | B16: Tareas del cliente con volumen, costo y tiempo actual.
A17: 4. Opportunities | B17: Oportunidades identificadas con impact/feasibility/velocity/fit.
A18: 5. Dashboard | B18: Resumen ejecutivo con KPIs principales.
A19: 6. Sensitivity | B19: Análisis de sensibilidad ante cambios en asunciones clave.
A20: 7. Benchmarks | B20: Benchmarks por vertical para validar estimaciones.
A21: 8. Change_Log | B21: Historial de cambios al modelo.
A23: Contacto | B23: JM Consulting — javiercm1221.jm@gmail.com

Sheet Supuestos
A1: Supuestos base del cliente
A2: Concepto | B2: Valor | C2: Nota / fuente
A3: Nombre del cliente | B3: Acme Property Mgmt | C3: Completar
A4: Vertical | B4: Property Management | C4: Completar
A5: Geografía principal | B5: USA | C5: USA / LATAM
A6: Tamaño de empleados | B6: 50 | C6: Completar
A7: Horizonte de análisis (meses) | B7: 12 | C7: Default 12
A8: Tasa de descuento anual | B8: 0.1 | C8: Default 10%
A9: Costo hora promedio USD (ops team) | B9: 35 | C9: USA: 30-50; LATAM: 8-15
A10: Costo hora senior USD | B10: 75 | C10: USA: 60-120; LATAM: 20-40
A11: Factor de carga (benefits etc) | B11: 1.3 | C11: Default 1.30
A12: Moneda de reporte | B12: USD
A13: Fecha del audit | B13: =TODAY() -> 46130
A14: Analista JM | B14: Javier / CTO agent
A16: Referencias rápidas (black — calculated)
A17: Costo hora efectivo (con carga) | B17: =B9*B11 -> 45.5

Sheet Task_Map
A1: Task Map — tareas del cliente con volumen, tiempo y costo actual
A2: # | B2: Tarea | C2: Zona | D2: Frecuencia | E2: Volumen mensual | F2: Minutos/ocurrencia | G2: Horas/mes | H2: Ejecutor (role) | I2: Costo hora USD | J2: Costo mensual USD | K2: Costo anual USD | L2: Nota
A3: 1 | B3: Clasificación de leads entrantes | C3: Adquisición | D3: Diaria | E3: 800 | F3: 4 | G3: =E3*F3/60 -> 53.333333 | H3: 28 | J3: =G3*I3 -> 0 | K3: =J3*12 -> 0
A4: 2 | B4: Respuesta inicial a inquilino | C4: Adquisición | D4: Diaria | E4: 1200 | F4: 5 | G4: =E4*F4/60 -> 100 | H4: 28 | J4: =G4*I4 -> 0 | K4: =J4*12 -> 0
A5: 3 | B5: Ingreso de solicitud de mantenimiento | C5: Retención | D5: Diaria | E5: 300 | F5: 6 | G5: =E5*F5/60 -> 30 | H5: 22 | J5: =G5*I5 -> 0 | K5: =J5*12 -> 0
A6: 4 | B6: Reconciliación de pagos mensuales | C6: Back-office | D6: Semanal | E6: 120 | F6: 45 | G6: =E6*F6/60 -> 90 | H6: 32 | J6: =G6*I6 -> 0 | K6: =J6*12 -> 0
A7: 5 | B7: Generación de reporte owner | C7: Back-office | D7: Mensual | E7: 60 | F7: 30 | G7: =E7*F7/60 -> 30 | H7: 32 | J7: =G7*I7 -> 0 | K7: =J7*12 -> 0
A8: 6 | B8: Screening de tenant (data entry) | C8: Adquisición | D8: Diaria | E8: 200 | F8: 12 | G8: =E8*F8/60 -> 40 | H8: 28 | J8: =G8*I8 -> 0 | K8: =J8*12 -> 0
A9: 7 | B9: Seguimiento de renovaciones | C9: Retención | D9: Mensual | E9: 50 | F9: 25 | G9: =E9*F9/60 -> 20.833333 | H9: 40 | J9: =G9*I9 -> 0 | K9: =J9*12 -> 0
A10: 8 | B10: Onboarding de nueva propiedad | C10: Entrega | D10: Semanal | E10: 10 | F10: 180 | G10: =E10*F10/60 -> 30 | H10: 40 | J10: =G10*I10 -> 0 | K10: =J10*12 -> 0
A11: 9 | B11: Categorización de facturas | C11: Back-office | D11: Semanal | E11: 400 | F11: 3 | G11: =E11*F11/60 -> 20 | H11: 32 | J11: =G11*I11 -> 0 | K11: =J11*12 -> 0
A12: 10 | B12: Preparación de eviction notices | C12: Retención | D12: Mensual | E12: 20 | F12: 45 | G12: =E12*F12/60 -> 15 | H12: 40 | J12: =G12*I12 -> 0 | K12: =J12*12 -> 0
B13: TOTAL | G13: =SUM(G3:G12) -> 429.16667 | J13: =SUM(J3:J12) -> 0 | K13: =SUM(K3:K12) -> 0

Sheet Opportunities
A1: Opportunity Matrix — oportunidades priorizadas
A2: # | B2: Oportunidad | C2: Task_Map ref | D2: Horas/mes | E2: Impact (1-5) | F2: Feasibility (1-5) | G2: Velocity (1-5) | H2: Strategic fit (1-5) | I2: Score (ponderado) | J2: Ahorro anual USD | K2: Revenue anual USD | L2: Implementación USD | M2: Retainer anual USD | N2: Payback meses | O2: ROI año 1 | P2: Categoría
A3: 1 | B3: Lead classifier + auto-response | C3: 1,2,6 | D3: 80 | E3: 5 | F3: 4 | G3: 5 | H3: 5 | I3: =E3*0.5+F3*0.2+G3*0.2+H3*0.1 -> 4.8 | J3: 60000 | K3: 18000 | L3: 6000 | N3: =IFERROR(L3/(((J3+K3)-M3)/12),0) -> 0.92307692 | O3: =IFERROR(((J3+K3)-M3-L3)/L3,0) -> 12 | P3: =IF(AND(E3>=4,F3>=4),"Quick Win",IF(AND(E3>=4,F3<=2),"Big Swing",IF(AND(E3<=2,F3>=4),"Nice-to-have","Deprioritize"))) -> Quick Win
A4: 2 | B4: Maintenance request triage | C4: 3 | D4: 30 | E4: 4 | F4: 4 | G4: 4 | H4: 4 | I4: =E4*0.5+F4*0.2+G4*0.2+H4*0.1 -> 4 | J4: 0 | K4: 12000 | L4: 3000 | N4: =IFERROR(L4/(((J4+K4)-M4)/12),0) -> 3 | O4: =IFERROR(((J4+K4)-M4-L4)/L4,0) -> 3 | P4: =IF(AND(E4>=4,F4>=4),"Quick Win",IF(AND(E4>=4,F4<=2),"Big Swing",IF(AND(E4<=2,F4>=4),"Nice-to-have","Deprioritize"))) -> Quick Win
A5: 3 | B5: Payment reconciliation agent | C5: 4,9 | D5: 35 | E5: 5 | F5: 3 | G5: 3 | H5: 4 | I5: =E5*0.5+F5*0.2+G5*0.2+H5*0.1 -> 4.1 | J5: 0 | K5: 25000 | L5: 6000 | N5: =IFERROR(L5/(((J5+K5)-M5)/12),0) -> 2.88 | O5: =IFERROR(((J5+K5)-M5-L5)/L5,0) -> 3.1666667 | P5: =IF(AND(E5>=4,F5>=4),"Quick Win",IF(AND(E5>=4,F5<=2),"Big Swing",IF(AND(E5<=2,F5>=4),"Nice-to-have","Deprioritize"))) -> Deprioritize
A6: 4 | B6: Owner report generator | C6: 5 | D6: 30 | E6: 4 | F6: 4 | G6: 4 | H6: 3 | I6: =E6*0.5+F6*0.2+G6*0.2+H6*0.1 -> 3.9 | J6: 0 | K6: 12000 | L6: 3000 | N6: =IFERROR(L6/(((J6+K6)-M6)/12),0) -> 3 | O6: =IFERROR(((J6+K6)-M6-L6)/L6,0) -> 3 | P6: =IF(AND(E6>=4,F6>=4),"Quick Win",IF(AND(E6>=4,F6<=2),"Big Swing",IF(AND(E6<=2,F6>=4),"Nice-to-have","Deprioritize"))) -> Quick Win
A7: 5 | B7: Tenant screening automation | C7: 6 | D7: 40 | E7: 4 | F7: 3 | G7: 3 | H7: 3 | I7: =E7*0.5+F7*0.2+G7*0.2+H7*0.1 -> 3.5 | J7: 0 | K7: 20000 | L7: 4500 | N7: =IFERROR(L7/(((J7+K7)-M7)/12),0) -> 2.7 | O7: =IFERROR(((J7+K7)-M7-L7)/L7,0) -> 3.4444444 | P7: =IF(AND(E7>=4,F7>=4),"Quick Win",IF(AND(E7>=4,F7<=2),"Big Swing",IF(AND(E7<=2,F7>=4),"Nice-to-have","Deprioritize"))) -> Deprioritize
A8: 6 | B8: Renewal nudger | C8: 7 | D8: 20 | E8: 3 | F8: 5 | G8: 5 | H8: 3 | I8: =E8*0.5+F8*0.2+G8*0.2+H8*0.1 -> 3.8 | J8: 30000 | K8: 8000 | L8: 2500 | N8: =IFERROR(L8/(((J8+K8)-M8)/12),0) -> 0.78947368 | O8: =IFERROR(((J8+K8)-M8-L8)/L8,0) -> 14.2 | P8: =IF(AND(E8>=4,F8>=4),"Quick Win",IF(AND(E8>=4,F8<=2),"Big Swing",IF(AND(E8<=2,F8>=4),"Nice-to-have","Deprioritize"))) -> Deprioritize
A9: 7 | B9: Onboarding workflow | C9: 8 | D9: 30 | E9: 3 | F9: 3 | G9: 3 | H9: 3 | I9: =E9*0.5+F9*0.2+G9*0.2+H9*0.1 -> 3 | J9: 10000 | K9: 15000 | L9: 2500 | N9: =IFERROR(L9/(((J9+K9)-M9)/12),0) -> 1.2 | O9: =IFERROR(((J9+K9)-M9-L9)/L9,0) -> 9 | P9: =IF(AND(E9>=4,F9>=4),"Quick Win",IF(AND(E9>=4,F9<=2),"Big Swing",IF(AND(E9<=2,F9>=4),"Nice-to-have","Deprioritize"))) -> Deprioritize
A10: 8 | B10: Invoice categorizer | C10: 9 | D10: 20 | E10: 3 | F10: 5 | G10: 5 | H10: 3 | I10: =E10*0.5+F10*0.2+G10*0.2+H10*0.1 -> 3.8 | J10: 0 | K10: 8000 | L10: 2000 | N10: =IFERROR(L10/(((J10+K10)-M10)/12),0) -> 3 | O10: =IFERROR(((J10+K10)-M10-L10)/L10,0) -> 3 | P10: =IF(AND(E10>=4,F10>=4),"Quick Win",IF(AND(E10>=4,F10<=2),"Big Swing",IF(AND(E10<=2,F10>=4),"Nice-to-have","Deprioritize"))) -> Deprioritize
A11: 9 | B11: Eviction notice automation | C11: 10 | D11: 15 | E11: 3 | F11: 4 | G11: 4 | H11: 3 | I11: =E11*0.5+F11*0.2+G11*0.2+H11*0.1 -> 3.4 | J11: 0 | K11: 10000 | L11: 2000 | N11: =IFERROR(L11/(((J11+K11)-M11)/12),0) -> 2.4 | O11: =IFERROR(((J11+K11)-M11-L11)/L11,0) -> 4 | P11: =IF(AND(E11>=4,F11>=4),"Quick Win",IF(AND(E11>=4,F11<=2),"Big Swing",IF(AND(E11<=2,F11>=4),"Nice-to-have","Deprioritize"))) -> Deprioritize
B12: TOTAL | J12: =SUM(J3:J11) -> 100000 | K12: =SUM(K3:K11) -> 128000 | L12: =SUM(L3:L11) -> 31500 | M12: =SUM(M3:M11) -> 0

Sheet Dashboard
A1: Dashboard ejecutivo — ROI resumen
A3: Cliente | B3: =Supuestos!B3 -> Acme Property Mgmt
A4: Vertical | B4: =Supuestos!B4 -> Property Management
A5: Fecha del audit | B5: =Supuestos!B13 -> 46130
A7: Tareas analizadas | B7: =COUNTA(Task_Map!B3:B12) -> 10 | C7: # de tareas en el Task Map
A8: Costo actual mensual (mapeado) | B8: =Task_Map!J13 -> 0 | C8: USD/mes
A9: Costo actual anual (mapeado) | B9: =Task_Map!K13 -> 0 | C9: USD/año
A11: Oportunidades identificadas | B11: =COUNTA(Opportunities!B3:B11) -> 9
A12: Ahorro anual estimado | B12: =Opportunities!J12 -> 100000 | C12: Suma ahorros año 1
A13: Revenue adicional estimado | B13: =Opportunities!K12 -> 128000 | C13: Suma revenue año 1
A14: Impacto total anual | B14: =Opportunities!J12+Opportunities!K12 -> 228000
A16: Inversión implementación total | B16: =Opportunities!L12 -> 31500 | C16: One-time USD
A17: Retainer anual total | B17: =Opportunities!M12 -> 0 | C17: Mantenimiento mensual * 12
A18: Costo total año 1 | B18: =N15+O15 -> 0 | C18: Implementación + retainer
A20: Benefit neto año 1 | B20: =M13-P16 -> 0 | C20: Impacto - costo
A21: ROI año 1 | B21: =IFERROR(S18/P16,0) -> 0 | C21: Benefit / Costo
A22: Payback promedio meses | B22: =IFERROR(P16/(M13/12),0) -> 0
A24: Benefit acumulado año 2 | B24: =(M13-O15) -> 0 | C24: Sólo retainer año 2 en adelante
A25: Benefit acumulado año 3 | B25: =(M13-O15)*2+M13-P16 -> 0

Sheet Sensitivity
A1: Análisis de sensibilidad
A3: Variación del ROI año 1 ante cambios en asunciones clave
A5: Adopción efectiva \ Sobrecosto implementación | B5: -0.2 | C5: 0 | D5: 0.2 | E5: 0.4
A6: 0.5 | B6: =IFERROR(((Dashboard!B15*$A6)-Dashboard!B17-Dashboard!B16*(1+-0.2))/(Dashboard!B16*(1+-0.2)),0) -> -1 | C6: =IFERROR(((Dashboard!B15*$A6)-Dashboard!B17-Dashboard!B16*(1+0))/(Dashboard!B16*(1+0)),0) -> -1 | D6: =IFERROR(((Dashboard!B15*$A6)-Dashboard!B17-Dashboard!B16*(1+0.2))/(Dashboard!B16*(1+0.2)),0) -> -1 | E6: =IFERROR(((Dashboard!B15*$A6)-Dashboard!B17-Dashboard!B16*(1+0.4))/(Dashboard!B16*(1+0.4)),0) -> -1
A7: 0.7 | B7: =IFERROR(((Dashboard!B15*$A7)-Dashboard!B17-Dashboard!B16*(1+-0.2))/(Dashboard!B16*(1+-0.2)),0) -> -1 | C7: =IFERROR(((Dashboard!B15*$A7)-Dashboard!B17-Dashboard!B16*(1+0))/(Dashboard!B16*(1+0)),0) -> -1 | D7: =IFERROR(((Dashboard!B15*$A7)-Dashboard!B17-Dashboard!B16*(1+0.2))/(Dashboard!B16*(1+0.2)),0) -> -1 | E7: =IFERROR(((Dashboard!B15*$A7)-Dashboard!B17-Dashboard!B16*(1+0.4))/(Dashboard!B16*(1+0.4)),0) -> -1
A8: 0.8 | B8: =IFERROR(((Dashboard!B15*$A8)-Dashboard!B17-Dashboard!B16*(1+-0.2))/(Dashboard!B16*(1+-0.2)),0) -> -1 | C8: =IFERROR(((Dashboard!B15*$A8)-Dashboard!B17-Dashboard!B16*(1+0))/(Dashboard!B16*(1+0)),0) -> -1 | D8: =IFERROR(((Dashboard!B15*$A8)-Dashboard!B17-Dashboard!B16*(1+0.2))/(Dashboard!B16*(1+0.2)),0) -> -1 | E8: =IFERROR(((Dashboard!B15*$A8)-Dashboard!B17-Dashboard!B16*(1+0.4))/(Dashboard!B16*(1+0.4)),0) -> -1
A9: 0.9 | B9: =IFERROR(((Dashboard!B15*$A9)-Dashboard!B17-Dashboard!B16*(1+-0.2))/(Dashboard!B16*(1+-0.2)),0) -> -1 | C9: =IFERROR(((Dashboard!B15*$A9)-Dashboard!B17-Dashboard!B16*(1+0))/(Dashboard!B16*(1+0)),0) -> -1 | D9: =IFERROR(((Dashboard!B15*$A9)-Dashboard!B17-Dashboard!B16*(1+0.2))/(Dashboard!B16*(1+0.2)),0) -> -1 | E9: =IFERROR(((Dashboard!B15*$A9)-Dashboard!B17-Dashboard!B16*(1+0.4))/(Dashboard!B16*(1+0.4)),0) -> -1
A10: 1 | B10: =IFERROR(((Dashboard!B15*$A10)-Dashboard!B17-Dashboard!B16*(1+-0.2))/(Dashboard!B16*(1+-0.2)),0) -> -1 | C10: =IFERROR(((Dashboard!B15*$A10)-Dashboard!B17-Dashboard!B16*(1+0))/(Dashboard!B16*(1+0)),0) -> -1 | D10: =IFERROR(((Dashboard!B15*$A10)-Dashboard!B17-Dashboard!B16*(1+0.2))/(Dashboard!B16*(1+0.2)),0) -> -1 | E10: =IFERROR(((Dashboard!B15*$A10)-Dashboard!B17-Dashboard!B16*(1+0.4))/(Dashboard!B16*(1+0.4)),0) -> -1
A11: 1.1 | B11: =IFERROR(((Dashboard!B15*$A11)-Dashboard!B17-Dashboard!B16*(1+-0.2))/(Dashboard!B16*(1+-0.2)),0) -> -1 | C11: =IFERROR(((Dashboard!B15*$A11)-Dashboard!B17-Dashboard!B16*(1+0))/(Dashboard!B16*(1+0)),0) -> -1 | D11: =IFERROR(((Dashboard!B15*$A11)-Dashboard!B17-Dashboard!B16*(1+0.2))/(Dashboard!B16*(1+0.2)),0) -> -1 | E11: =IFERROR(((Dashboard!B15*$A11)-Dashboard!B17-Dashboard!B16*(1+0.4))/(Dashboard!B16*(1+0.4)),0) -> -1
A14: Interpretación:
A15: Verde: ROI > 100% (resultado sólido)
A16: Amarillo: ROI 25%-100% (resultado aceptable)
A17: Rojo: ROI < 25% (revisar scope, pricing o timing)

Sheet Benchmarks
A1: Benchmarks por vertical (data propia + mercado)
A2: Vertical | B2: Caso típico | C2: Ahorro anual USD | D2: Revenue anual USD | E2: Implementación USD | F2: Notas
A3: Property Management | B3: Lead response accelerator | C3: 60000 | D3: 180000 | E3: 18000 | F3: Cliente 300-500 unidades
A4: Property Management | B4: Maintenance triage | C4: 25000 | D4: 0 | E4: 15000
A5: Property Management | B5: Owner report generation | C5: 18000 | D5: 0 | E5: 12000
A6: Accounting Firm (mid) | B6: Document extraction | C6: 80000 | D6: 0 | E6: 22000 | F6: Firma 10-30 contadores
A7: Accounting Firm (mid) | B7: Reconciliation agent | C7: 45000 | D7: 0 | E7: 18000
A8: Accounting Firm (mid) | B8: Client reporting agent | C8: 35000 | D8: 0 | E8: 15000
A9: Legal Boutique | B9: Document review | C9: 90000 | D9: 0 | E9: 25000 | F9: Firma 5-20 abogados
A10: Legal Boutique | B10: Contract analysis | C10: 55000 | D10: 0 | E10: 20000
A11: Logistics | B11: Dispatch optimization | C11: 120000 | D11: 30000 | E11: 30000 | F11: Flota 50+ vehículos
A12: Logistics | B12: Document automation | C12: 40000 | D12: 0 | E12: 15000
A13: Healthcare | B13: Intake automation | C13: 70000 | D13: 50000 | E13: 25000 | F13: Clínica 10+ staff
A14: Healthcare | B14: Prior auth assistant | C14: 90000 | D14: 0 | E14: 28000
A15: Manufacturing | B15: Quality inspection | C15: 100000 | D15: 0 | E15: 35000 | F15: Planta mid-size
A16: B2B SaaS | B16: Support auto-resolve | C16: 60000 | D16: 0 | E16: 18000 | F16: 500+ tickets/mes
A17: B2B SaaS | B17: Lead qualification | C17: 40000 | D17: 80000 | E17: 15000

Sheet Change_Log
A1: Change log
A2: Fecha | B2: Autor | C2: Descripción del cambio | D2: Versión
A3: 2026-04-18 | B3: Javier CM | C3: Versión inicial del modelo maestro con 8 sheets y estructura completa. | D3: v1.0.0
